asciiracer/__init__.py
asciiracer/__main__.py
asciiracer/ascii_factory.py
asciiracer/config.py
asciiracer/environment.py
asciiracer/game.py
asciiracer/hud.py
asciiracer/mechanics.py
asciiracer/misc.py
asciiracer-1.0.3.dist-info/LICENSE
asciiracer-1.0.3.dist-info/METADATA
asciiracer-1.0.3.dist-info/WHEEL
asciiracer-1.0.3.dist-info/entry_points.txt
asciiracer-1.0.3.dist-info/top_level.txt
asciiracer-1.0.3.dist-info/RECORD
