Metadata-Version: 2.1
Name: asciiracer
Version: 1.0.3
Summary: A racing game that runs in terminal
Home-page: https://github.com/UpGado/ascii_racer
Author: Ahmed Gado
Author-email: ahmedehabg@gmail.com
License: UNKNOWN
Platform: UNKNOWN
Classifier: Programming Language :: Python :: 3
Classifier: License :: OSI Approved :: MIT License
Classifier: Operating System :: OS Independent
Requires-Python: >=3.6.0
Requires-Dist: windows-curses (>=2.0) ; platform_system == "Windows"
